{
    "uid": [
        {
            "value": 1
        }
    ],
    "uuid": [
        {
            "value": "1debb16e-cb5e-4b21-a25f-3baec837baef"
        }
    ],
    "langcode": [
        {
            "value": "en"
        }
    ],
    "preferred_langcode": [
        {
            "value": "en"
        }
    ],
    "preferred_admin_langcode": [],
    "name": [
        {
            "value": "admin"
        }
    ],
    "mail": [
        {
            "value": "verbruggenalex@gmail.com"
        }
    ],
    "timezone": [
        {
            "value": "UTC"
        }
    ],
    "status": [
        {
            "value": true
        }
    ],
    "created": [
        {
            "value": "2022-05-04T15:59:57+00:00",
            "format": "Y-m-d\\TH:i:sP"
        }
    ],
    "changed": [
        {
            "value": "2022-05-04T15:59:57+00:00",
            "format": "Y-m-d\\TH:i:sP"
        }
    ],
    "roles": [],
    "default_langcode": [
        {
            "value": true
        }
    ],
    "path": [
        {
            "alias": null,
            "pid": null,
            "langcode": "en",
            "pathauto": 0
        }
    ]
}